unopass/__init__.py
unopass/unopass.py
unopass-0.0.21.dist-info/LICENSE
unopass-0.0.21.dist-info/METADATA
unopass-0.0.21.dist-info/WHEEL
unopass-0.0.21.dist-info/top_level.txt
unopass-0.0.21.dist-info/RECORD
