Metadata-Version: 2.1
Name: unopass
Version: 0.0.21
Summary: unopass is a convenient python module that allows you to retrieve secrets from the 1Password CLI
Home-page: https://github.com/amadotejada/unopass
Author: Amado Tejada
Author-email: tejada.amado@gmail.com
Classifier: Programming Language :: Python :: 3
Classifier: License :: OSI Approved :: MIT License
Classifier: Operating System :: OS Independent
Requires-Python: >=3.6
License-File: LICENSE
